quickbot_agent/__init__.py
quickbot_agent/config.py
quickbot_agent/main.py
quickbot_agent/utils.py
quickbot_agent/handlers/messages.py
quickbot_agent/model/__init__.py
quickbot_agent/model/message_log.py
quickbot_agent-0.1.0.dist-info/licenses/LICENSE
quickbot_agent-0.1.0.dist-info/METADATA
quickbot_agent-0.1.0.dist-info/WHEEL
quickbot_agent-0.1.0.dist-info/top_level.txt
quickbot_agent-0.1.0.dist-info/RECORD
