Metadata-Version: 2.4
Name: quickbot-agent
Version: 0.1.0
Summary: Adds AI answers and API orchestration to your bot
Author-email: Alexander Kalinovsky <ak@botforge.biz>
License: MIT License
Classifier: Programming Language :: Python :: 3
Classifier: Operating System :: OS Independent
Classifier: Development Status :: 3 - Alpha
Requires-Python: >=3.13
License-File: LICENSE
Requires-Dist: quickbot>=0.1.1
Requires-Dist: openai>=1.97.1
Requires-Dist: pydantic>=2.11.7
Provides-Extra: dev
Requires-Dist: build>=1.2.1; extra == "dev"
Requires-Dist: twine>=5.0.0; extra == "dev"
Requires-Dist: pytest>=8.0.0; extra == "dev"
Requires-Dist: ruff>=0.5.0; extra == "dev"
Dynamic: license-file
